pyrus/__init__.py
pyrus/client.py
pyrus/models/__init__.py
pyrus/models/constants.py
pyrus/models/customhandlers.py
pyrus/models/entities.py
pyrus/models/requests.py
pyrus/models/responses.py
pyrus_api-2.31.1.dist-info/LICENSE.txt
pyrus_api-2.31.1.dist-info/METADATA
pyrus_api-2.31.1.dist-info/WHEEL
pyrus_api-2.31.1.dist-info/top_level.txt
pyrus_api-2.31.1.dist-info/zip-safe
pyrus_api-2.31.1.dist-info/RECORD
