Metadata-Version: 2.1
Name: pyrus-api
Version: 2.31.1
Summary: Python Pyrus API client
Home-page: https://pyrus.com/en/help/api
Author: Pyrus
Author-email: contact@pyrus.com
License: MIT License
Project-URL: GitHub Project, https://github.com/simplygoodsoftware/pyrusapi-python
Keywords: pyrus api
Platform: UNKNOWN
Requires-Python: >=3.4
Requires-Dist: requests
Requires-Dist: jsonpickle
